craynn/__init__.py
craynn/dag/__init__.py
craynn/dag/common.py
craynn/dag/meta.py
craynn/dag/evaluate/__init__.py
craynn/dag/evaluate/common.py
craynn/dag/evaluate/dynamic.py
craynn/dag/evaluate/static.py
craynn/dag/lang/__init__.py
craynn/dag/lang/achain.py
craynn/dag/lang/language.py
craynn/dag/lang/selector.py
craynn/info/__init__.py
craynn/info/layers.py
craynn/layers/__init__.py
craynn/layers/common.py
craynn/layers/dense_ops.py
craynn/layers/gates.py
craynn/layers/meta.py
craynn/layers/noise_ops.py
craynn/layers/conv_ops/__init__.py
craynn/layers/conv_ops/_conv.py
craynn/layers/conv_ops/_pool.py
craynn/layers/conv_ops/_upscale.py
craynn/layers/conv_ops/conv_utils.py
craynn/networks/__init__.py
craynn/networks/meta.py
craynn/networks/utils.py
craynn/nonlinearities/__init__.py
craynn/nonlinearities/common.py
craynn/nonlinearities/defaults.py
craynn/nonlinearities/meta.py
craynn/objectives/__init__.py
craynn/objectives/classification.py
craynn/objectives/elbo.py
craynn/objectives/regression.py
craynn/objectives/regularization.py
craynn/parameters/__init__.py
craynn/parameters/common.py
craynn/parameters/decomposition.py
craynn/parameters/defaults.py
craynn/parameters/glorot.py
craynn/parameters/masked.py
craynn/parameters/meta.py
craynn/parameters/noisy.py
craynn/parameters/orthogonal.py
craynn/parameters/restricted.py
craynn/parameters/utils.py
craynn/subnetworks/__init__.py
craynn/subnetworks/gates.py
craynn/subnetworks/meta.py
craynn/subnetworks/residual_nets.py
craynn/subnetworks/skip.py
craynn/train/__init__.py
craynn/train/common.py
craynn/updates/__init__.py
craynn/updates/array.py
craynn/updates/common.py
craynn/updates/meta.py
craynn/updates/subsets.py
craynn/updates/utils.py
craynn/utils/__init__.py
craynn/utils/axes.py
craynn/utils/clazz.py
craynn/utils/func.py
craynn/utils/math.py
craynn/viz/__init__.py
craynn/viz/common.py
craynn/viz/viz.py
craynn-0.4.0.dist-info/LICENSE
craynn-0.4.0.dist-info/METADATA
craynn-0.4.0.dist-info/WHEEL
craynn-0.4.0.dist-info/top_level.txt
craynn-0.4.0.dist-info/RECORD
