Metadata-Version: 2.1
Name: craynn
Version: 0.4.0
Summary: Yet another neural network toolkit.
Home-page: https://gitlab.com/craynn/craynn
Author: Maxim Borisyak and contributors.
Author-email: maximus.been@gmail.com
Maintainer: Maxim Borisyak
Maintainer-email: maximus.been@gmail.com
License: MIT
Classifier: Development Status :: 4 - Beta
Classifier: Intended Audience :: Science/Research
Classifier: License :: OSI Approved :: MIT License
Classifier: Programming Language :: Python :: 3
Requires-Python: >=3.7
License-File: LICENSE
Requires-Dist: jax >=0.3.8
Requires-Dist: numpy >=1.17.0
Requires-Dist: matplotlib >=3.0.2
Requires-Dist: pydotplus >=2.0.2
Provides-Extra: test
Requires-Dist: pytest >=4.0.0 ; extra == 'test'
Requires-Dist: scipy >=1.3.0 ; extra == 'test'
